LICENSE
MANIFEST.in
README.rst
requirements.txt
setup.py
dapp/__init__.py
dapp.egg-info/PKG-INFO
dapp.egg-info/SOURCES.txt
dapp.egg-info/dependency_links.txt
dapp.egg-info/requires.txt
dapp.egg-info/top_level.txt
test/__init__.py
test/communicator_test_case.py
test/test_client.py
test/test_general.py
test/test_server.py