Metadata-Version: 1.1
Name: dapp
Version: 0.3.0
Summary: Library implementing DevAssistant PingPong protocol
Home-page: UNKNOWN
Author: Bohuslav "Slavek" Kabrda
Author-email: bkabrda@redhat.com
License: GPLv2+
Keywords: devassistant,pipe,protocol,pingpong
Platform: UNKNOWN
Classifier: Development Status :: 3 - Alpha
Classifier: Intended Audience :: Developers
Classifier: License :: OSI Approved :: GNU General Public License v2 or later (GPLv2+)
Classifier: Operating System :: POSIX :: Linux
Classifier: Programming Language :: Python
